notion_py_client/__init__.py
notion_py_client/api_types.py
notion_py_client/helper.py
notion_py_client/notion_client.py
notion_py_client/py.typed
notion_py_client/utils.py
notion_py_client/blocks/__init__.py
notion_py_client/blocks/base.py
notion_py_client/blocks/layout_blocks.py
notion_py_client/blocks/media_blocks.py
notion_py_client/blocks/special_blocks.py
notion_py_client/blocks/text_blocks.py
notion_py_client/blocks/unsupported.py
notion_py_client/filters/__init__.py
notion_py_client/filters/advanced_filters.py
notion_py_client/filters/base_filters.py
notion_py_client/filters/compound_filters.py
notion_py_client/filters/date_filters.py
notion_py_client/filters/property_filters.py
notion_py_client/filters/relation_filters.py
notion_py_client/filters/timestamp_filters.py
notion_py_client/filters/value_filters.py
notion_py_client/models/__init__.py
notion_py_client/models/cover.py
notion_py_client/models/date_info.py
notion_py_client/models/file.py
notion_py_client/models/formula.py
notion_py_client/models/icon.py
notion_py_client/models/parent.py
notion_py_client/models/rich_text_item.py
notion_py_client/models/select_option.py
notion_py_client/models/status_option.py
notion_py_client/models/unique_id.py
notion_py_client/models/user.py
notion_py_client/models/verification.py
notion_py_client/models/primitives/__init__.py
notion_py_client/models/primitives/annotation.py
notion_py_client/models/primitives/custom_emoji.py
notion_py_client/models/primitives/empty_object.py
notion_py_client/models/primitives/equation.py
notion_py_client/models/primitives/link_mention.py
notion_py_client/models/primitives/link_preview.py
notion_py_client/models/primitives/mention.py
notion_py_client/models/primitives/template_mention.py
notion_py_client/models/primitives/text_item.py
notion_py_client/properties/__init__.py
notion_py_client/properties/relation_property.py
notion_py_client/properties/rollup_property.py
notion_py_client/properties/base_properties/__init__.py
notion_py_client-0.1.16.dist-info/METADATA
notion_py_client-0.1.16.dist-info/WHEEL
notion_py_client-0.1.16.dist-info/licenses/LICENSE
notion_py_client-0.1.16.dist-info/RECORD
