Metadata-Version: 2.4
Name: notion-py-client
Version: 0.1.16
Summary: A Python client for Notion API
Project-URL: Homepage, https://higashi-masafumi.github.io/notion-py/
Project-URL: Repository, https://github.com/higashi-masafumi/notion-py
Project-URL: Issues, https://github.com/higashi-masafumi/notion-py/issues
Author-email: Masafumi Higashi <cruiseeast@gmail.com>
License-Expression: MIT
License-File: LICENSE
Classifier: License :: OSI Approved :: MIT License
Classifier: Operating System :: OS Independent
Classifier: Programming Language :: Python :: 3
Requires-Python: >=3.10
Requires-Dist: httpx>=0.28.1
Requires-Dist: pydantic>=2.11.10
